cff2toml/CITATION.cff
cff2toml/__init__.py
cff2toml/main.py
cff2toml/cli/__init__.py
cff2toml/cli/app.py
cff2toml/cli/command_metadata_output.py
cff2toml/cli/context_helpers.py
cff2toml/cli/about_command/__init__.py
cff2toml/cli/about_command/about_command.py
cff2toml/cli/change_command/__init__.py
cff2toml/cli/change_command/change_command.py
cff2toml/cli/view_command/__init__.py
cff2toml/cli/view_command/view_command.py
cff2toml/models/__init__.py
cff2toml/models/basic_model.py
cff2toml/models/metadata.py
cff2toml/models/agents/__init__.py
cff2toml/models/agents/authors/cff_entity_author.py
cff2toml/models/agents/authors/cff_person_author.py
cff2toml/models/agents/authors/pyproject_toml_author.py
cff2toml/models/agents/authors/synchronizers/cff_and_pyproject_toml_author_synchronizer.py
cff2toml/models/agents/organizations/cff_entity.py
cff2toml/models/agents/people/cff_person.py
cff2toml/models/agents/people/human_name.py
cff2toml/models/files/__init__.py
cff2toml/models/files/cff_file.py
cff2toml/models/files/metadata_file.py
cff2toml/models/files/pyproject_toml_file.py
cff2toml/models/files/toml_file.py
cff2toml/models/files/synchronizers/__init__.py
cff2toml/models/files/synchronizers/cff_and_pyproject_toml_file_synchronizer.py
cff2toml-3.2.2.dist-info/METADATA
cff2toml-3.2.2.dist-info/WHEEL
cff2toml-3.2.2.dist-info/entry_points.txt
cff2toml-3.2.2.dist-info/licenses/LICENSE
cff2toml-3.2.2.dist-info/RECORD
