Metadata-Version: 2.3
Name: cff2toml
Version: 3.2.2
Summary: A module to synchronize metadata between TOML and CFF files, including between pyproject.toml and CITATION.cff files.
Project-URL: Documentation, https://github.com/willynilly/cff2toml#readme
Project-URL: Issues, https://github.com/willynilly/cff2toml/issues
Project-URL: Source, https://github.com/willynilly/cff2toml
Author-email: Will Riley <wanderingwill@gmail.com>
License-Expression: Apache-2.0
License-File: LICENSE
Classifier: Development Status :: 3 - Alpha
Classifier: Intended Audience :: Developers
Classifier: Intended Audience :: Education
Classifier: Intended Audience :: Information Technology
Classifier: Intended Audience :: Science/Research
Classifier: Intended Audience :: System Administrators
Classifier: License :: OSI Approved :: Apache Software License
Classifier: Natural Language :: English
Classifier: Programming Language :: Python
Classifier: Programming Language :: Python :: 3
Classifier: Programming Language :: Python :: 3.8
Classifier: Programming Language :: Python :: 3.9
Classifier: Programming Language :: Python :: 3.10
Classifier: Programming Language :: Python :: 3.11
Classifier: Programming Language :: Python :: 3.12
Classifier: Topic :: Scientific/Engineering
Classifier: Topic :: Software Development
Classifier: Topic :: Utilities
Requires-Python: >=3.8
Requires-Dist: pydantic>=2.6.4
Requires-Dist: pydash>=8.0.0
Requires-Dist: pyyaml>=6.0.1
Requires-Dist: tomlkit>=0.12.4
Requires-Dist: typer>=0.12.1
Provides-Extra: testing
Requires-Dist: pytest>=8.1.1; extra == 'testing'
